ocaclient/__init__.py
ocaclient/client.py
ocaclient/models.py
ocaclient/version.py
ocaclient-0.8.1.dist-info/LICENCE
ocaclient-0.8.1.dist-info/METADATA
ocaclient-0.8.1.dist-info/WHEEL
ocaclient-0.8.1.dist-info/top_level.txt
ocaclient-0.8.1.dist-info/RECORD
