Metadata-Version: 2.1
Name: ocaclient
Version: 0.8.1
Summary: A very simple client for OCA's web services.
Home-page: https://git.sr.ht/~whynothugo/ocaclient
Author: Hugo Osvaldo Barrera
Author-email: hugo@barrera.io
License: ISC
Classifier: Development Status :: 5 - Production/Stable
Classifier: Environment :: Web Environment
Classifier: Intended Audience :: Developers
Classifier: License :: OSI Approved :: ISC License (ISCL)
Classifier: Operating System :: POSIX
Classifier: Programming Language :: Python :: 3 :: Only
Classifier: Programming Language :: Python :: 3
Classifier: Programming Language :: Python :: 3.7
Classifier: Programming Language :: Python :: 3.8
Classifier: Programming Language :: Python :: 3.9
Classifier: Programming Language :: Python :: 3.10
Classifier: Topic :: Internet :: WWW/HTTP
Classifier: Topic :: Software Development :: Libraries :: Python Modules
License-File: LICENCE
Requires-Dist: python-dateutil
Requires-Dist: lxml
Requires-Dist: zeep (>=3.0.0)
Provides-Extra: dev
Requires-Dist: ipython ; extra == 'dev'
Requires-Dist: mypy ; extra == 'dev'
Requires-Dist: types-python-dateutil ; extra == 'dev'
